{
    "0": [
        "S",
        "L",
        "D",
        "G",
        "P",
        "K"
    ],
    "1": [
        "S",
        "W",
        "Y"
    ],
    "2": [
        "S",
        "L",
        "F",
        "O"
    ],
    "3": [
        "L",
        "D",
        "N",
        "H"
    ],
    "4": [
        "S",
        "L",
        "W",
        "A"
    ],
    "5": [
        "S",
        "B",
        "M",
        "X",
        "U"
    ],
    "6": [
        "S",
        "W",
        "T",
        "Y"
    ],
    "7": [
        "T",
        "F",
        "B",
        "I",
        "V",
        "E"
    ],
    "8": [
        "S",
        "M",
        "R",
        "Q",
        "J"
    ],
    "9": [
        "S",
        "W",
        "T",
        "C",
        "Z"
    ]
}