{
    "0": [
        "E",
        "N",
        "S",
        "T"
    ],
    "1": [
        "C",
        "H",
        "F",
        "R",
        "L",
        "O"
    ],
    "2": [
        "B",
        "U",
        "Q"
    ],
    "3": [
        "N"
    ],
    "4": [
        "B",
        "P",
        "K"
    ],
    "5": [
        "B",
        "G",
        "E"
    ],
    "6": [
        "B",
        "G"
    ],
    "7": [
        "B",
        "V",
        "I",
        "J",
        "A"
    ],
    "8": [
        "B",
        "G"
    ],
    "9": [
        "B",
        "P",
        "D",
        "M"
    ]
}