{
    "A": "Synovial_WBC <= 15980.0",
    "B": "Segment > 66.5",
    "C": "Serum_ESR <= 30.5",
    "D": "Serum_CRP <= 148.5",
    "E": "Serum_ESR <= 38.0",
    "F": "Total_Elixhauser_Groups_per_record <= 2.5",
    "G": "Segment > 50.5",
    "H": "Hb > 12.5",
    "I": "two_positive_culture == False",
    "J": "Synovial_WBC <= 5703.0",
    "K": "Serum_ESR <= 29.0",
    "L": "Serum_CRP <= 87.5",
    "M": "Synovial_WBC <= 4013.0",
    "N": "Hb > 10.0",
    "O": "Serum_CRP <= 38.5",
    "P": "Segment <= 71.5",
    "Q": "Positive_Histology == False",
    "R": "Synovial_PMN <= 89.5",
    "S": "Serum_ESR <= 38.5",
    "T": "Purulence == False",
    "U": "Synovial_PMN <= 3.0",
    "V": "Serum_ESR <= 48.5",
    "W": "Serum_ESR <= 28.0",
    "X": "Age > 45.5",
    "Y": "Serum_CRP <= 6.5",
    "Z": "Segment > 63.5",
    "a": "Surgery == True",
    "b": "APTT <= 28.5"
}