{
    "0": [
        "P",
        "K",
        "J",
        "L",
        "I",
        "E",
        "B"
    ],
    "1": [
        "M",
        "F",
        "U"
    ],
    "2": [
        "G",
        "Q",
        "N"
    ],
    "3": [
        "G",
        "Q",
        "R"
    ],
    "4": [
        "P",
        "M",
        "K",
        "J",
        "L"
    ],
    "5": [
        "M",
        "F",
        "T"
    ],
    "6": [
        "P",
        "G",
        "A"
    ],
    "7": [
        "P",
        "C",
        "H"
    ],
    "8": [
        "G",
        "V",
        "O"
    ],
    "9": [
        "P",
        "D",
        "S"
    ]
}