{
    "0": [
        "E",
        "P",
        "M"
    ],
    "1": [
        "G",
        "B"
    ],
    "2": [
        "G",
        "H",
        "F"
    ],
    "3": [
        "G",
        "R"
    ],
    "4": [
        "G",
        "D"
    ],
    "5": [
        "G",
        "E",
        "A",
        "J",
        "I"
    ],
    "6": [
        "H",
        "R",
        "N"
    ],
    "7": [
        "G",
        "A",
        "Q",
        "O",
        "K"
    ],
    "8": [
        "G",
        "R"
    ],
    "9": [
        "G",
        "H",
        "J",
        "Q",
        "L",
        "C"
    ]
}