{
    "0": [
        "C",
        "N",
        "O"
    ],
    "1": [
        "N",
        "I",
        "R",
        "W",
        "B"
    ],
    "2": [
        "N",
        "G",
        "T",
        "D",
        "Y"
    ],
    "3": [
        "C",
        "I",
        "J",
        "V",
        "S"
    ],
    "4": [
        "G",
        "F",
        "L"
    ],
    "5": [
        "J",
        "T",
        "V",
        "Z",
        "M"
    ],
    "6": [
        "C",
        "A"
    ],
    "7": [
        "C",
        "X",
        "U"
    ],
    "8": [
        "C",
        "A",
        "P",
        "H"
    ],
    "9": [
        "I",
        "J",
        "K",
        "Q",
        "E"
    ]
}