{
    "A": "Positive_Histology == True",
    "B": "Purulence == True",
    "C": "Age > 29.0",
    "D": "two_positive_culture == False",
    "E": "Synovial_PMN <= 63.0",
    "F": "Age > 68.5",
    "G": "APTT <= 32.5",
    "H": "Serum_ESR <= 32.0",
    "I": "Hb <= 11.0",
    "J": "Serum_CRP >= 15.0",
    "K": "Total_CCI >= 1.0",
    "L": "Segment >= 88.0",
    "M": "PLATELET < 355.0",
    "N": "Serum_CRP >= 15.0",
    "O": "P_T >= 10.0",
    "P": "Serum_CRP >= 15.0",
    "Q": "Synovial_WBC <= 5391.0",
    "R": "Segment >= 88.0",
    "S": "Serum_CRP >= 15.0",
    "T": "Synovial_WBC >= 5391.0",
    "U": "Serum_WBC_ >= 13.0",
    "V": "Serum_WBC_ >= 13.0",
    "W": "APTT >= 28.0",
    "X": "Serum_ESR <= 32.0"
}