{
    "A": "Synovial_WBC <= 4608.5",
    "B": "P_T <= 10.5",
    "C": "two_positive_culture == False",
    "D": "Synovial_WBC <= 3650.0",
    "E": "Age > 62.5",
    "F": "Synovial_WBC <= 8280.0",
    "G": "Positive_Histology == True",
    "H": "Synovial_WBC <= 3763.0",
    "I": "Synovial_WBC <= 43473.0",
    "J": "APTT <= 28.5",
    "K": "Synovial_PMN >= 79.0",
    "L": "Serum_ESR >= 44.0",
    "M": "APTT >= 28.0",
    "N": "Serum_ESR <= 44.0",
    "O": "PLATELET >= 281.0",
    "P": "Serum_ESR <= 44.0",
    "Q": "Segment < 72.0",
    "R": "Serum_CRP >= 26.0",
    "S": "PLATELET >= 281.0",
    "T": "P_T >= 9.0",
    "U": "Segment < 70.5",
    "V": "Serum_ESR <= 44.0",
    "W": "P_T >= 9.0",
    "X": "Serum_WBC_ < 8.5",
    "Y": "Serum_CRP >= 26.0",
    "Z": "Serum_WBC_ < 11.5",
    "a": "Serum_ESR <= 44.0",
    "b": "Hb <= 12.0",
    "c": "Hb <= 12.0",
    "d": "Serum_ESR <= 44.0",
    "e": "Synovial_PMN >= 79.0"
}