{
    "0": [
        "L",
        "H",
        "F"
    ],
    "1": [
        "D",
        "U",
        "A",
        "C"
    ],
    "2": [
        "L",
        "D",
        "H"
    ],
    "3": [
        "D",
        "U",
        "S",
        "E"
    ],
    "4": [
        "L",
        "D",
        "J",
        "K"
    ],
    "5": [
        "L",
        "H",
        "J",
        "I"
    ],
    "6": [
        "D",
        "U",
        "S",
        "O",
        "W",
        "G"
    ],
    "7": [
        "L",
        "S",
        "J",
        "N",
        "Q"
    ]
}