{
    "0": [
        "B"
    ],
    "1": [
        "H",
        "D",
        "C"
    ],
    "2": [
        "J",
        "C"
    ],
    "3": [
        "J",
        "T",
        "F"
    ],
    "4": [
        "E",
        "A"
    ],
    "5": [
        "J",
        "A"
    ],
    "6": [
        "J",
        "H",
        "T",
        "E",
        "Q"
    ],
    "7": [
        "J",
        "H",
        "T",
        "K"
    ],
    "8": [
        "D",
        "F",
        "Q",
        "M",
        "I"
    ]
}