{
    "A": "Purulence == True",
    "B": "Positive_Histology == True",
    "C": "two_positive_culture == False",
    "D": "Serum_CRP >= 117.0",
    "E": "Age <= 46.0",
    "F": "Synovial_WBC >= 81496.0",
    "G": "Synovial_WBC >= 81496.0",
    "H": "Segment < 70.5",
    "I": "Synovial_WBC >= 81496.0",
    "J": "Serum_ESR >= 104.0",
    "K": "PLATELET >= 371.0",
    "L": "Synovial_PMN >= 89.0",
    "M": "Serum_CRP >= 117.0",
    "N": "Serum_WBC_ >= 14.0",
    "O": "P_T < 11.5",
    "P": "Serum_CRP >= 117.0",
    "Q": "Synovial_WBC >= 81496.0",
    "R": "Serum_ESR >= 104.0",
    "S": "Synovial_PMN >= 89.0",
    "T": "Synovial_PMN >= 89.0",
    "U": "Segment >= 70.0",
    "V": "Synovial_WBC >= 81496.0",
    "W": "Serum_ESR >= 104.0",
    "X": "PLATELET >= 371.0",
    "Y": "Hb <= 9.0",
    "Z": "Hb <= 9.0",
    "a": "Serum_CRP >= 117.0",
    "b": "APTT >= 33.0",
    "c": "PLATELET >= 371.0"
}