{
    "0": [
        "C",
        "V",
        "H",
        "D"
    ],
    "1": [
        "C",
        "A",
        "O",
        "N"
    ],
    "2": [
        "C",
        "O",
        "K",
        "N"
    ],
    "3": [
        "K",
        "E",
        "B"
    ],
    "4": [
        "C",
        "O",
        "F"
    ],
    "5": [
        "C",
        "V",
        "A",
        "G",
        "I"
    ],
    "6": [
        "C",
        "K",
        "G"
    ],
    "7": [
        "A",
        "G",
        "F",
        "P",
        "J"
    ],
    "8": [
        "C",
        "V",
        "H",
        "Q",
        "S"
    ]
}