{
    "A": "Synovial_PMN > 54.0",
    "B": "Synovial_PMN > 51.5",
    "C": "two_positive_culture == False",
    "D": "Synovial_PMN > 55.5",
    "E": "Positive_Histology == False",
    "F": "Purulence == False",
    "G": "Synovial_PMN > 76.5",
    "H": "Surgery == True",
    "I": "Synovial_PMN <= 79.0",
    "J": "Serum_CRP <= 8.0",
    "K": "Segment <= 66.0",
    "L": "Serum_CRP <= 8.0",
    "M": "Total_CCI <= 0.0",
    "N": "Synovial_WBC <= 700.0",
    "O": "Segment <= 66.0",
    "P": "Single_Positive_culture <= 0.0",
    "Q": "Synovial_WBC <= 700.0",
    "R": "Serum_ESR <= 3.0",
    "S": "Segment >= 66.0",
    "T": "Hb >= 16.0",
    "U": "Serum_ESR <= 3.0",
    "V": "APTT <= 28.0"
}